[{"school":"\u7d79\u7fa9\u52d9\u4e2d","date_held":"2025-01-22","target":"7\u5e74","name":"\u7560\u5c71\u5948\u5948","category":"\u7d20\u8a71","title":"\u91d1\u306e\u9aea"},{"school":"\u7d79\u7fa9\u52d9\u4e2d","date_held":"2025-01-22","target":"8\u5e74","name":"\u9234\u6728\u6e05\u5b50","category":"\u7d20\u8a71","title":"\u5c71\u306e\u4e0a\u306e\u706b"},{"school":"\u7d79\u7fa9\u52d9\u4e2d","date_held":"2025-01-22","target":"9\u5e74","name":"\u4e09\u6a4b\u7f8e\u6075\u5b50","category":"\u7d20\u8a71","title":"\u706b\u306e\u9ce5\u3068\u738b\u5973\u30ef\u30b7\u30ea\u30fc\u30b5"}]